{
    "type": "asset",
    "name": "jQuery slicknav",
    "vendor url": "https:\/\/github.com\/ComputerWolf\/SlickNav",
    "download url": "https:\/\/github.com\/ComputerWolf\/SlickNav",
    "variants": {
        "minified": {
            "css": {
                "base": [
                    "slicknav.css"
                ]
            },
            "js": [
                "jquery.slicknav.min.js"
            ]
        }
    },
    "css": {
        "base": [
            "slicknav.css"
        ]
    },
    "js": [
        "jquery.slicknav.js"
    ],
    "version_detector": {
        "id": "static",
        "configuration": {
            "version": "0.0.1"
        }
    }
}